visualwm/__init__.py
visualwm/cli.py
visualwm/core/__init__.py
visualwm/core/checksum.py
visualwm/core/device.py
visualwm/core/info.py
visualwm/core/style.py
visualwm/document/__init__.py
visualwm/document/excel.py
visualwm/document/ofd.py
visualwm/document/pdf.py
visualwm/document/word.py
visualwm/font/NotoSerifSC-VariableFont_wght.ttf
visualwm/image/__init__.py
visualwm/image/watermark.py
visualwm/text/__init__.py
visualwm/text/watermark.py
visualwm/video/__init__.py
visualwm/video/watermark.py
visualwm-1.2.0.dist-info/licenses/LICENSE
visualwm-1.2.0.dist-info/METADATA
visualwm-1.2.0.dist-info/WHEEL
visualwm-1.2.0.dist-info/entry_points.txt
visualwm-1.2.0.dist-info/top_level.txt
visualwm-1.2.0.dist-info/RECORD
