Metadata-Version: 2.4
Name: visualwm
Version: 1.2.0
Summary: 泄密警示明水印SDK - 支持图片、视频、文本、文档多模态水印嵌入与提取
Home-page: https://github.com/example/visualwm
Author: VisualWM Team
Author-email: VisualWM Team <visualwm@example.com>
Maintainer-email: VisualWM Team <visualwm@example.com>
License: MIT
Project-URL: Homepage, https://github.com/example/visualwm
Project-URL: Documentation, https://github.com/example/visualwm#readme
Project-URL: Repository, https://github.com/example/visualwm.git
Project-URL: Issues, https://github.com/example/visualwm/issues
Keywords: watermark,security,image,video,pdf,document,traceability,leakage-prevention
Classifier: Development Status :: 4 - Beta
Classifier: Intended Audience :: Developers
Classifier: Intended Audience :: Information Technology
Classifier: License :: OSI Approved :: MIT License
Classifier: Operating System :: OS Independent
Classifier: Programming Language :: Python :: 3
Classifier: Programming Language :: Python :: 3.8
Classifier: Programming Language :: Python :: 3.9
Classifier: Programming Language :: Python :: 3.10
Classifier: Programming Language :: Python :: 3.11
Classifier: Programming Language :: Python :: 3.12
Classifier: Topic :: Security
Classifier: Topic :: Multimedia :: Graphics
Classifier: Topic :: Multimedia :: Video
Classifier: Topic :: Office/Business
Requires-Python: >=3.8
License-File: LICENSE
Requires-Dist: Pillow>=9.0.0
Requires-Dist: opencv-python>=4.5.0
Requires-Dist: numpy>=1.20.0
Requires-Dist: python-docx>=0.8.11
Requires-Dist: PyPDF2>=3.0.0
Requires-Dist: reportlab>=3.6.0
Requires-Dist: openpyxl>=3.0.0
Requires-Dist: lxml>=4.9.0
Requires-Dist: imageio-ffmpeg>=0.4.8
Provides-Extra: ocr
Requires-Dist: pytesseract>=0.3.10; extra == "ocr"
Provides-Extra: dev
Requires-Dist: pytest>=7.0.0; extra == "dev"
Requires-Dist: pytest-cov>=4.0.0; extra == "dev"
Requires-Dist: black>=22.0.0; extra == "dev"
Requires-Dist: flake8>=5.0.0; extra == "dev"
Requires-Dist: build>=0.10.0; extra == "dev"
Requires-Dist: twine>=4.0.0; extra == "dev"
Provides-Extra: all
Requires-Dist: visualwm[ocr]; extra == "all"
Dynamic: author
Dynamic: home-page
Dynamic: license-file
Dynamic: requires-python
